[{"name":"Aldo PATRICIELLO","twitter":"@PatricielloAldo","url":null,"euro":null},{"name":"Alessandra BASSO","twitter":"@alebassoMEP","url":null,"euro":null},{"name":"Alessandra MORETTI","twitter":"@ale_moretti","url":null,"euro":null},{"name":"Alessandro PANZA","twitter":"@alepanzaoff","url":null,"euro":null},{"name":"Andrea CAROPPO","twitter":"@caroppo_andrea","url":null,"euro":null},{"name":"Andrea COZZOLINO","twitter":"@cozzolino62","url":null,"euro":null},{"name":"Angelo CIOCCA","twitter":"@AngeloCiocca","url":null,"euro":null},{"name":"Anna BONFRISCO","twitter":"@bonfriscoanna","url":null,"euro":null},{"name":"Annalisa TARDINO","twitter":"@TardinoAnnalisa","url":null,"euro":null},{"name":"Antonio Maria RINALDI","twitter":"@Rinaldi_euro","url":null,"euro":null},{"name":"Antonio TAJANI","twitter":"@Antonio_Tajani","url":null,"euro":null},{"name":"Brando BENIFEI","twitter":"@brandobenifei","url":null,"euro":null},{"name":"Carlo CALENDA","twitter":"@CarloCalenda","url":null,"euro":null},{"name":"Carlo FIDANZA","twitter":"@FidanzaCarlo","url":null,"euro":null},{"name":"Caterina CHINNICI","twitter":"@CaterinaChinnic","url":null,"euro":null},{"name":"Chiara GEMMA","twitter":"@chgemma68","url":null,"euro":null},{"name":"Daniela RONDINELLI","twitter":"@Dani_Rondinelli","url":null,"euro":null},{"name":"Danilo Oscar LANCINI","twitter":"@DOscarLancini","url":null,"euro":null},{"name":"Dino GIARRUSSO","twitter":"@DinoGiarrusso","url":null,"euro":null},{"name":"Elena LIZZI","twitter":"@elenalizzi","url":null,"euro":null},{"name":"Eleonora EVI","twitter":"@EleonoraEvi","url":null,"euro":null},{"name":"Elisabetta GUALMINI","twitter":"@gualminielisa","url":null,"euro":null},{"name":"Fabio Massimo CASTALDO","twitter":"@FMCastaldo","url":null,"euro":null},{"name":"Francesca DONATO","twitter":"@ladyonorato","url":null,"euro":null},{"name":"Franco ROBERTI","twitter":"@francorobertieu","url":null,"euro":null},{"name":"Fulvio MARTUSCIELLO","twitter":"@fulviomartuscie","url":null,"euro":null},{"name":"Gianantonio DA RE","twitter":"@GianantonioDaRe","url":null,"euro":null},{"name":"Gianna GANCIA","twitter":"@giannagancia","url":null,"euro":null},{"name":"Giuliano PISAPIA","twitter":"@giulianopisapia","url":null,"euro":null},{"name":"Giuseppe FERRANDINO","twitter":"@giosiferrandino","url":null,"euro":null},{"name":"Giuseppe MILAZZO","twitter":"@giuseppemilaz11","url":null,"euro":null},{"name":"Herbert DORFMANN","twitter":"@HerbertDorfmann","url":null,"euro":null},{"name":"Ignazio CORRAO","twitter":"@ignaziocorrao","url":null,"euro":null},{"name":"Irene TINAGLI","twitter":"@itinagli","url":null,"euro":null},{"name":"Isabella ADINOLFI","twitter":"@Isa_Adinolfi","url":null,"euro":null},{"name":"Isabella TOVAGLIERI","twitter":"@isatovaglieri","url":null,"euro":null},{"name":"Laura FERRARA","twitter":"@LFerraraM5S","url":null,"euro":null},{"name":"Lucia VUOLO","twitter":"@LuciaVuoloEU","url":null,"euro":null},{"name":"Luisa REGIMENTI","twitter":"@luisaregimenti","url":null,"euro":null},{"name":"Mara BIZZOTTO","twitter":"@marabizzotto","url":null,"euro":null},{"name":"Marco CAMPOMENOSI","twitter":"@MCampomenosi","url":null,"euro":null},{"name":"Marco DREOSTO","twitter":"@MarcoDreosto","url":null,"euro":null},{"name":"Marco ZANNI","twitter":"@Marcozanni86","url":null,"euro":null},{"name":"Marco ZULLO","twitter":"@MarcoZullo","url":null,"euro":null},{"name":"Mario FURORE","twitter":"@MarioFurore","url":null,"euro":null},{"name":"Massimiliano SALINI","twitter":"@MaxSalini","url":null,"euro":null},{"name":"Massimiliano SMERIGLIO","twitter":"@maxsmeriglio","url":null,"euro":null},{"name":"Massimo CASANOVA","twitter":"@MassimoCasanov3","url":null,"euro":null},{"name":"Matteo ADINOLFI","twitter":"@adinolfi_matteo","url":null,"euro":null},{"name":"Nicola DANTI","twitter":"@DantiNicola","url":null,"euro":null},{"name":"Nicola PROCACCINI","twitter":"@NProcaccini","url":null,"euro":null},{"name":"Paolo BORCHIA","twitter":"@PaoloBorchia","url":null,"euro":null},{"name":"Paolo DE CASTRO","twitter":"@paolodecastro","url":null,"euro":null},{"name":"Patrizia TOIA","twitter":"@toiapatrizia","url":null,"euro":null},{"name":"Pierfrancesco MAJORINO","twitter":"@pfmajorino","url":null,"euro":null},{"name":"Piernicola PEDICINI","twitter":"@PediciniM5S","url":null,"euro":null},{"name":"Pietro BARTOLO","twitter":"@bartolopietro1","url":null,"euro":null},{"name":"Pietro FIOCCHI","twitter":"@FiocchiPietro","url":null,"euro":null},{"name":"Pina PICIERNO","twitter":"@pinapic","url":null,"euro":null},{"name":"Raffaele FITTO","twitter":"@RaffaeleFitto","url":null,"euro":null},{"name":"Raffaele STANCANELLI","twitter":"@r_stancanelli","url":null,"euro":null},{"name":"Rosa D'AMATO","twitter":"@rosadamato634","url":null,"euro":null},{"name":"Rosanna CONTE","twitter":"@Rosannaconte_","url":null,"euro":null},{"name":"Sabrina PIGNEDOLI","twitter":"@SabriPignedoli","url":null,"euro":null},{"name":"Salvatore DE MEO","twitter":"@salv_de_meo","url":null,"euro":null},{"name":"Sergio BERLATO","twitter":"@SERGIOBERLATO","url":null,"euro":null},{"name":"Silvia SARDONE","twitter":"@SardoneSilvia","url":null,"euro":null},{"name":"Silvio BERLUSCONI","twitter":"@berlusconi","url":null,"euro":null},{"name":"Simona BALDASSARRE","twitter":"@SR_Baldassarre","url":null,"euro":null},{"name":"Simona BONAF\u00c8","twitter":"@simonabonafe","url":null,"euro":null},{"name":"Stefania ZAMBELLI","twitter":"@ZambelliLega","url":null,"euro":null},{"name":"Susanna CECCARDI","twitter":"@SusannaCeccardi","url":null,"euro":null},{"name":"Tiziana BEGHIN","twitter":"@beghin_t","url":null,"euro":null},{"name":"Valentino GRANT","twitter":"@ValentinoGrant","url":null,"euro":null},{"name":"Vincenzo SOFO","twitter":"@vincesofo","url":null,"euro":null}]